{
  "files": {
    "Arc Template": {
      "type": "arc",
      "status": "active",
      "links": [],
      "tags": [
        "#arc"
      ],
      "last_updated": "<% tp.date.now(\"YYYY-MM-DDTHH:mm:ss\") %>"
    },
    "Event Template": {
      "type": "event",
      "status": "active",
      "links": [],
      "tags": [
        "#event"
      ],
      "last_updated": "<% tp.date.now(\"YYYY-MM-DDTHH:mm:ss\") %>"
    },
    "Faction Template": {
      "type": "faction",
      "status": "active",
      "links": [],
      "tags": [
        "#faction"
      ],
      "last_updated": "<% tp.date.now(\"YYYY-MM-DDTHH:mm:ss\") %>"
    },
    "Hook Template": {
      "type": "hook",
      "status": "active",
      "links": [],
      "tags": [
        "#hook"
      ],
      "last_updated": "<% tp.date.now(\"YYYY-MM-DDTHH:mm:ss\") %>"
    },
    "Item Template": {
      "type": "item",
      "status": "active",
      "links": [],
      "tags": [
        "#item"
      ],
      "last_updated": "<% tp.date.now(\"YYYY-MM-DDTHH:mm:ss\") %>"
    },
    "Location Template": {
      "type": "location",
      "status": "active",
      "links": [],
      "tags": [
        "#location"
      ],
      "last_updated": "<% tp.date.now(\"YYYY-MM-DDTHH:mm:ss\") %>"
    },
    "Lore Template": {
      "type": "lore",
      "status": "active",
      "links": [],
      "tags": [
        "#location"
      ],
      "last_updated": "<% tp.date.now(\"YYYY-MM-DDTHH:mm:ss\") %>"
    },
    "NPC Template": {
      "type": "npc",
      "status": "active",
      "links": [],
      "tags": [
        "#npc"
      ],
      "last_updated": "<% tp.date.now(\"YYYY-MM-DDTHH:mm:ss\") %>"
    },
    "Player Template": {
      "type": "player",
      "status": "active",
      "links": [],
      "tags": [
        "#player"
      ],
      "last_updated": "<% tp.date.now(\"YYYY-MM-DDTHH:mm:ss\") %>"
    },
    "Session Template": {
      "type": "session",
      "status": "active",
      "links": [],
      "tags": [
        "#session"
      ],
      "last_updated": "<% tp.date.now(\"YYYY-MM-DDTHH:mm:ss\") %>"
    },
    "Spren Template": {
      "type": "spren",
      "status": "active",
      "links": [],
      "tags": [
        "#spren"
      ],
      "last_updated": "<% tp.date.now(\"YYYY-MM-DDTHH:mm:ss\") %>"
    },
    "01 Truthkeepers Arc": {
      "type": "arc",
      "status": "completed",
      "links": [
        "[[Adjudicator Peton]]",
        "[[Truthkeepers]]",
        "[[Possessed]]",
        "[[High Witness Yeshan]]",
        "[[Chip]]",
        "[[Sila]]",
        "[[Knights of Dusk]]",
        "[[Lavrik]]",
        "[[Highlady Marise Sathir]]",
        "[[Citylord Nilar Yenev]]",
        "[[Dillind]]",
        "[[Morrow]]",
        "[[1172-01-11 The Arrival]]",
        "[[1172-01-12 The Shellmite Attack]]",
        "[[1172-01-35 Morrow's Execution]]",
        "[[000 Arrival]]",
        "[[001 First Blood]]",
        "[[002 Whitespine]]",
        "[[003 Yenev and the Axe]]",
        "[[004 The Sathir Estate]]",
        "[[005 Hearthstone]]",
        "[[006 Dillind and the Temple]]",
        "[[007 Lavrik and the Soulcaster]]",
        "[[008 The Envisagers of Talinan]]",
        "[[009 Slavers]]",
        "[[010 Soulcaster and Shared Employers]]",
        "[[011 Promotions and Revolar]]"
      ],
      "tags": [
        "#arc"
      ],
      "last_updated": "2026-05-16T12:00:00"
    },
    "02 Knights of Dusk Arc": {
      "type": "arc",
      "status": "active",
      "links": [
        "[[Truthkeepers]]",
        "[[Revolar]]",
        "[[Knights of Dusk]]",
        "[[Silent Oath]]",
        "[[High Enforcer Aylen]]",
        "[[Istrum]]",
        "[[Ojog]]",
        "[[General Spade]]",
        "[[Khria]]",
        "[[Beric Quinn]]",
        "[[Ghostbloods]]",
        "[[Undertaker]]",
        "[[Sweeper]]",
        "[[Chip]]",
        "[[Bloodmarks]]",
        "[[Arbiter Jalis]]",
        "[[Grand Justicar Malice]]",
        "[[1172-02-16 The Stackhouse Slavers]]",
        "[[1172-02-17 Meeting at the Whitespine]]",
        "[[1172-02-18 Meeting with the Undertaker]]",
        "[[1172-02-22 The Foundry Chase]]",
        "[[012 Following Chip]]",
        "[[013 Shadow War in the Driftwards]]"
      ],
      "tags": [
        "#arc",
        "#revolar",
        "#rebellion"
      ],
      "last_updated": "2024-05-25T10:00:00"
    },
    "03 Stormblessed Arc": {
      "type": "arc",
      "status": "planned",
      "links": [
        "[[Tien]]",
        "[[Kaladin]]",
        "[[Tomat]]",
        "[[Amaram]]",
        "[[Sons of Honor]]",
        "[[Dillind]]",
        "[[Ghostbloods]]",
        "[[Helaran]]",
        "[[Silent Oath]]",
        "[[Hook: The Orphans of Tomat]]",
        "[[Hook: Resonance of the Past]]",
        "[[Hook: Helaran's Shadow]]",
        "[[Hook: The Stormblessed Investigation]]"
      ],
      "tags": [
        "#arc",
        "#stormblessed",
        "#border_skirmish"
      ],
      "last_updated": "2024-05-22T10:00:00"
    },
    "04 Nurian Gems Arc": {
      "type": "arc",
      "status": "planned",
      "links": [
        "[[Nurian Gems]]",
        "[[N'tal]]",
        "[[Bloodmarks]]",
        "[[Kuma]]",
        "[[Szeth-son-son-Vallano]]",
        "[[Ghostbloods]]",
        "[[Undertaker]]",
        "[[Grand Justicar Malice]]",
        "[[Bodenar]]",
        "[[Vorn]]",
        "[[Ilsh]]",
        "[[1172-03-42 The Experimental Steamship]]",
        "[[The Steamship's Secret]]"
      ],
      "tags": [
        "#arc",
        "#jah_keved",
        "#nurian_gems"
      ],
      "last_updated": "2026-05-17T12:00:00"
    },
    "05 Kharbranth Infiltration Arc": {
      "type": "arc",
      "status": "planned",
      "links": [
        "[[Ghostbloods]]",
        "[[Kharbranth]]",
        "[[Jasnah Kholin]]",
        "[[Kabsal]]",
        "[[Shallan Davar]]"
      ],
      "tags": [
        "#arc",
        "#kharbranth",
        "#infiltration",
        "#ghostbloods"
      ],
      "last_updated": "2026-05-18T12:00:00"
    },
    "Fina": {
      "type": "player",
      "status": "active",
      "links": [
        "[[Verdae]]",
        "[[Bloodmarks]]",
        "[[N'tal]]",
        "[[Undertaker]]",
        "[[The Highlord's Greed]]"
      ],
      "tags": [
        "#player",
        "#edgedancer",
        "#alethi",
        "#noble",
        "#lighteyed"
      ],
      "last_updated": "2024-05-25T10:00:00"
    },
    "Galeth-son-Thald": {
      "type": "player",
      "status": "active",
      "links": [
        "[[Kun'ahu]]",
        "[[Szeth-son-son-Vallano]]",
        "[[The Axelsmith]]",
        "[[Neturo]]"
      ],
      "tags": [
        "#player",
        "#shin",
        "#warrior",
        "#exiled",
        "#stoneward",
        "#darkeyed"
      ],
      "last_updated": "2024-05-18T00:00:00"
    },
    "Iiko": {
      "type": "player",
      "status": "active",
      "links": [
        "[[Dreamwaker]]",
        "[[Revolar]]",
        "[[Ardent Kaelis]]",
        "[[The Devotary Call]]"
      ],
      "tags": [
        "#player",
        "#truthwatcher",
        "#nurian",
        "#envoy"
      ],
      "last_updated": "2026-05-20T12:00:00"
    },
    "Kuma": {
      "type": "player",
      "status": "active",
      "links": [
        "[[Viscose]]",
        "[[Revolar]]",
        "[[Nurian Gems]]",
        "[[1172-03-42 The Experimental Steamship]]",
        "[[04 Nurian Gems Arc]]",
        "[[Hook: Resonance of the Past]]",
        "[[New Technology]]",
        "[[Ilsh]]",
        "[[Vorn]]"
      ],
      "tags": [
        "#player",
        "#elsecaller",
        "#nurian",
        "#maker"
      ],
      "last_updated": "2024-05-22T10:00:00"
    },
    "Mallow": {
      "type": "player",
      "status": "active",
      "links": [
        "[[Cadence]]",
        "[[Truthkeepers]]",
        "[[Khria]]",
        "[[The Orphans of Tomat]]",
        "[[Tracking the Knights of Dusk]]"
      ],
      "tags": [
        "#player",
        "#willshaper",
        "#purelaker",
        "#enforcer"
      ],
      "last_updated": "2024-05-25T10:00:00"
    },
    "N'tal": {
      "type": "player",
      "status": "active",
      "links": [
        "[[Pyre]]",
        "[[Sun's Zenith]]",
        "[[Slipmarket]]",
        "[[Bloodmarks]]",
        "[[Undertaker]]",
        "[[Fina]]",
        "[[Revolar]]",
        "[[Arbiter Jalis]]",
        "[[N'tal's Vendetta]]",
        "[[1172-02-17 The Foundry Chase]]"
      ],
      "tags": [
        "#player",
        "#dustbringer",
        "#nurian",
        "#merchant"
      ],
      "last_updated": "2024-05-25T10:00:00"
    },
    "Adjudicator Peton": {
      "type": "npc",
      "status": "active",
      "links": [
        "[[Truthkeepers]]",
        "[[Revolar]]"
      ],
      "tags": [
        "#npc",
        "#lighteyed",
        "#alethi",
        "#adjudicator",
        "#traditionalist"
      ],
      "last_updated": "2026-05-15T12:00:00"
    },
    "Amaram": {
      "type": "npc",
      "status": "active",
      "links": [
        "[[Sadeas Princedom]]",
        "[[Tomat]]",
        "[[Sons of Honor]]",
        "[[Hearthstone]]",
        "[[House Sathir|Sathir Estate]]",
        "[[Helaran]]",
        "[[Tien]]"
      ],
      "tags": [
        "#npc",
        "#lighteyed",
        "#alethi",
        "#sons_of_honor"
      ],
      "last_updated": "2024-05-21T09:00:00"
    },
    "Arbiter Jalis": {
      "type": "npc",
      "status": "active",
      "links": [
        "[[Bloodmarks]]",
        "[[Revolar]]",
        "[[Grand Justicar Malice]]",
        "[[N'tal]]"
      ],
      "tags": [
        "#npc",
        "#bloodmarks",
        "#veden",
        "#antagonist"
      ],
      "last_updated": "2024-05-18T00:00:00"
    },
    "Ardent Kaelis": {
      "type": "npc",
      "status": "active",
      "links": [
        "[[Revolar]]",
        "[[Iiko]]",
        "[[The Devotary Call]]",
        "[[Tablet of Eleven Cities]]",
        "[[Ardent Vedelis]]"
      ],
      "tags": [
        "#npc",
        "#ardent",
        "#scholar",
        "#alethi"
      ],
      "last_updated": "2026-05-20T13:00:00"
    },
    "Ardent Vedelis": {
      "type": "npc",
      "status": "completed",
      "links": [
        "[[Knights of Dusk]]",
        "[[Lavrik]]",
        "[[Devotary of Sincerity]]",
        "[[Veristitalians]]",
        "[[Highlord Paladar]]",
        "[[Vamah Archivum]]",
        "[[General Spade]]",
        "[[Ardent Kaelis]]"
      ],
      "tags": [
        "#npc",
        "#ardent",
        "#scholar",
        "#veristitalian",
        "#alethi",
        "#soulcaster"
      ],
      "last_updated": "2026-05-20T13:00:00"
    },
    "Ashusa": {
      "type": "npc",
      "status": "active",
      "links": [
        "[[Vamah Princedom]]",
        "[[Alethkar]]",
        "[[Citylord Nilar Yenev]]",
        "[[Stringken]]"
      ],
      "tags": [
        "#npc",
        "#alethi"
      ],
      "last_updated": "2026-05-15T12:00:00"
    },
    "Beric Quinn": {
      "type": "npc",
      "status": "active",
      "links": [
        "[[Knights of Dusk]]",
        "[[Revolar]]",
        "[[Truthkeepers|Truthkeeper]]",
        "[[N'tal]]",
        "[[Kuma]]",
        "[[Ojog]]",
        "[[Truthkeeper Camp]]",
        "[[Stackhouses]]",
        "[[General Spade]]",
        "[[Truthkeepers]]",
        "[[Adjudicator Peton]]"
      ],
      "tags": [
        "#npc",
        "#lighteyed",
        "#nurian",
        "#hunter",
        "#rebel",
        "#spy",
        "#knights_of_dusk"
      ],
      "last_updated": "2024-05-24T12:00:00"
    },
    "Chip": {
      "type": "npc",
      "status": "active",
      "links": [
        "[[Ghostbloods]]",
        "[[Alethkar]]",
        "[[Truthkeepers]]",
        "[[1172-02-20 The Cinder Evacuation]]",
        "[[Karani]]",
        "[[Highlord Paladar]]"
      ],
      "tags": [
        "#npc",
        "#lighteyed",
        "#alethi",
        "#enforcer",
        "#spy",
        "#noble"
      ],
      "last_updated": "2026-05-18T12:00:00"
    },
    "Citylord Nilar Yenev": {
      "type": "npc",
      "status": "active",
      "links": [
        "[[Vamah Princedom]]",
        "[[Alethkar]]",
        "[[Stringken]]",
        "[[House Sathir]]",
        "[[Highlady Marise Sathir]]",
        "[[Highlord Paladar]]",
        "[[Bit]]",
        "[[Ashusa]]",
        "[[Dalen]]"
      ],
      "tags": [
        "#npc",
        "#lighteyed",
        "#alethi",
        "#stringken",
        "#citylord",
        "#bit"
      ],
      "last_updated": "2026-05-15T12:00:00"
    },
    "Dalen": {
      "type": "npc",
      "status": "active",
      "links": [
        "[[Sadeas Princedom]]",
        "[[Revolar]]",
        "[[House Sathir]]",
        "[[Highlady Marise Sathir]]",
        "[[Highlord Kethren Sathir]]",
        "[[Knights of Dusk]]"
      ],
      "tags": [
        "#npc",
        "#darkeyed",
        "#steward",
        "#alethi",
        "#house_sathir",
        "#revolar"
      ],
      "last_updated": "2024-05-19T14:00:00"
    },
    "Dillind": {
      "type": "npc",
      "status": "active",
      "links": [
        "[[Sadeas Princedom]]",
        "[[Tomat]]",
        "[[Tien]]"
      ],
      "tags": [
        "#npc",
        "#teenager"
      ],
      "last_updated": "2026-05-14T14:00:00"
    },
    "General Odrin Lesh": {
      "type": "npc",
      "status": "active",
      "links": [
        "[[Vamah Princedom]]",
        "[[Revolar]]",
        "[[Knights of Dusk]]",
        "[[Highlord Paladar]]",
        "[[General Spade]]"
      ],
      "tags": [
        "#npc",
        "#lighteyed",
        "#alethi",
        "#general",
        "#vamah_military"
      ],
      "last_updated": "2026-05-16T12:00:00"
    },
    "General Spade": {
      "type": "npc",
      "status": "active",
      "links": [
        "[[Knights of Dusk]]",
        "[[Revolar]]",
        "[[Truthkeepers]]",
        "[[Highlord Paladar]]",
        "[[General Odrin Lesh]]",
        "[[Silent Oath]]",
        "[[High Enforcer Aylen]]",
        "[[Lavrik]]",
        "[[Hook: The Fieldwards Heist]]"
      ],
      "tags": [
        "#npc",
        "#lighteyed",
        "#alethi",
        "#dustbringer",
        "#rebel_leader"
      ],
      "last_updated": "2024-05-23T10:00:00"
    },
    "Grand Justicar Malice": {
      "type": "npc",
      "status": "active",
      "links": [
        "[[Bloodmarks]]",
        "[[Bodenar]]",
        "[[Ghostbloods]]",
        "[[N'tal]]",
        "[[Arbiter Jalis]]"
      ],
      "tags": [
        "#npc",
        "#veden",
        "#bloodmarks",
        "#grand_justicar"
      ],
      "last_updated": "2026-05-17T12:00:00"
    },
    "Helaran": {
      "type": "npc",
      "status": "active",
      "links": [
        "[[Ghostbloods]]",
        "[[Tomat]]",
        "[[Amaram]]",
        "[[Shallan Davar]]"
      ],
      "tags": [
        "#npc",
        "#ghostbloods",
        "#assassin",
        "#veshers"
      ],
      "last_updated": "2026-05-18T12:00:00"
    },
    "High Enforcer Aylen": {
      "type": "npc",
      "status": "active",
      "links": [
        "[[Truthkeepers]]",
        "[[Revolar]]",
        "[[Possessed]]",
        "[[Knights of Dusk]]",
        "[[General Spade]]",
        "[[Khria]]",
        "[[High Witness Yeshan]]",
        "[[Istrum]]",
        "[[Morrow]]"
      ],
      "tags": [
        "#npc",
        "#darkeyed",
        "#makabaki",
        "#herald",
        "#high_enforcer"
      ],
      "last_updated": "2024-05-19T12:00:00"
    },
    "High Witness Yeshan": {
      "type": "npc",
      "status": "active",
      "links": [
        "[[Truthkeepers]]",
        "[[Tukkar]]",
        "[[Possessed]]",
        "[[High Enforcer Aylen]]"
      ],
      "tags": [
        "#npc",
        "#lighteyed",
        "#herald"
      ],
      "last_updated": "2024-05-19T12:00:00"
    },
    "Highlady Marise Sathir": {
      "type": "npc",
      "status": "active",
      "links": [
        "[[Sadeas Princedom]]",
        "[[House Sathir]]",
        "[[Dalen]]"
      ],
      "tags": [
        "#npc",
        "#lighteyed",
        "#alethi",
        "#highlady",
        "#house_sathir"
      ],
      "last_updated": "2026-05-13T23:35:12"
    },
    "Highlord Paladar": {
      "type": "npc",
      "status": "active",
      "links": [
        "[[Vamah Princedom]]",
        "[[Revolar]]",
        "[[General Spade]]",
        "[[General Odrin Lesh]]",
        "[[1172-02-20 The Cinder Evacuation]]",
        "[[Knights of Dusk]]",
        "[[Truthkeepers]]",
        "[[The Highlord's Greed]]",
        "[[Chip]]"
      ],
      "tags": [
        "#npc",
        "#lighteyed",
        "#alethi",
        "#highlord"
      ],
      "last_updated": "2026-05-20T12:00:00"
    },
    "Ilsh": {
      "type": "npc",
      "status": "active",
      "links": [
        "[[Bodenar]]",
        "[[Kuma]]",
        "[[Vorn]]"
      ],
      "tags": [
        "#npc",
        "#thaylen",
        "#researcher",
        "#ardent_imposter"
      ],
      "last_updated": "2026-05-16T17:00:00"
    },
    "Istrum": {
      "type": "npc",
      "status": "active",
      "links": [
        "[[Silent Oath]]",
        "[[Revolar]]",
        "[[High Enforcer Aylen]]",
        "[[Knights of Dusk]]",
        "[[Ojog]]"
      ],
      "tags": [
        "#npc",
        "#makabaki",
        "#skybreaker",
        "#truthkeeper"
      ],
      "last_updated": "2024-05-24T10:00:00"
    },
    "Jasnah Kholin": {
      "type": "npc",
      "status": "active",
      "links": [
        "[[Veristitalians]]",
        "[[Kharbranth]]",
        "[[Shallan Davar]]",
        "[[Kabsal]]"
      ],
      "tags": [
        "#npc",
        "#lighteyed",
        "#alethi",
        "#scholar",
        "#radiant",
        "#heretic"
      ],
      "last_updated": "2026-05-18T12:00:00"
    },
    "Jory": {
      "type": "npc",
      "status": "active",
      "links": [
        "[[Revolar]]",
        "[[Knights of Dusk]]",
        "[[Bloodmarks]]",
        "[[Stackhouses]]",
        "[[Arbiter Jalis]]"
      ],
      "tags": [
        "#npc",
        "#possessed",
        "#knights_of_dusk",
        "#radiant"
      ],
      "last_updated": "2024-05-18T00:00:00"
    },
    "Kabsal": {
      "type": "npc",
      "status": "active",
      "links": [
        "[[Ghostbloods]]",
        "[[Bodenar]]",
        "[[Jasnah Kholin]]",
        "[[Kharbranth]]",
        "[[Shallan Davar]]"
      ],
      "tags": [
        "#npc",
        "#ardent",
        "#ghostbloods"
      ],
      "last_updated": "2026-05-18T12:00:00"
    },
    "Karani": {
      "type": "npc",
      "status": "active",
      "links": [
        "[[Ghostbloods]]",
        "[[Revolar]]",
        "[[Sila]]",
        "[[Chip]]",
        "[[Tahs]]",
        "[[Fina]]"
      ],
      "tags": [
        "#npc",
        "#darkeyed",
        "#alethi",
        "#worldhopper",
        "#ghostbloods"
      ],
      "last_updated": "2026-05-13T23:35:12"
    },
    "Khria": {
      "type": "npc",
      "status": "active",
      "links": [
        "[[Knights of Dusk]]",
        "[[Revolar]]",
        "[[Truthkeepers]]",
        "[[Mallow]]",
        "[[Hook: The Fieldwards Heist]]",
        "[[General Spade]]"
      ],
      "tags": [
        "#npc",
        "#darkeyed",
        "#purelaker",
        "#truthwatcher",
        "#rebel"
      ],
      "last_updated": "2024-05-23T10:00:00"
    },
    "Lavrik": {
      "type": "npc",
      "status": "completed",
      "links": [
        "[[Knights of Dusk]]",
        "[[Ardent Vedelis]]"
      ],
      "tags": [
        "#npc",
        "#sergeant",
        "#rebel"
      ],
      "last_updated": "2026-05-20T13:00:00"
    },
    "Lila": {
      "type": "npc",
      "status": "active",
      "links": [
        "[[Knights of Dusk]]",
        "[[Revolar]]",
        "[[Slipmarket]]",
        "[[Fieldwards]]",
        "[[Stackhouse Slavers]]",
        "[[Khria]]",
        "[[General Spade]]",
        "[[The Vamah Archivum]]",
        "[[Stackhouses]]",
        "[[Bloodmarks]]",
        "[[Truthkeepers]]"
      ],
      "tags": [
        "#npc",
        "#darkeyed",
        "#alethi",
        "#revolar",
        "#informant"
      ],
      "last_updated": "2024-05-19T10:00:00"
    },
    "Lirin": {
      "type": "npc",
      "status": "active",
      "links": [
        "[[Hearthstone]]",
        "[[Toralin Roshone]]"
      ],
      "tags": [
        "#npc",
        "#darkeyed",
        "#surgeon"
      ],
      "last_updated": "2026-05-13T23:55:00"
    },
    "Mikeyel Franzay": {
      "type": "npc",
      "status": "active",
      "links": [
        "[[Sadeas Princedom]]",
        "[[House Sathir]]",
        "[[Highlady Marise Sathir]]",
        "[[Dalen]]"
      ],
      "tags": [
        "#npc",
        "#alethi",
        "#guard"
      ],
      "last_updated": "2026-05-13T23:45:00"
    },
    "Morrow": {
      "type": "npc",
      "status": "completed",
      "links": [
        "[[Revolar]]",
        "[[Truthkeepers]]",
        "[[Possessed]]",
        "[[High Enforcer Aylen]]",
        "[[Cryptics]]"
      ],
      "tags": [
        "#npc",
        "#darkeyed",
        "#alethi",
        "#merchant",
        "#possessed"
      ],
      "last_updated": "2026-05-16T15:00:00"
    },
    "Ojog": {
      "type": "npc",
      "status": "active",
      "links": [
        "[[Truthkeepers]]",
        "[[Revolar]]",
        "[[Truthkeeper Camp]]",
        "[[N'tal]]",
        "[[Kuma]]",
        "[[Beric Quinn]]",
        "[[Hearthstone]]",
        "[[Adjudicator Peton]]",
        "[[Istrum]]",
        "[[Silent Oath]]",
        "[[Knights of Dusk]]"
      ],
      "tags": [
        "#npc",
        "#nurian",
        "#truthkeeper",
        "#enforcer",
        "#assassin"
      ],
      "last_updated": "2024-05-24T12:00:00"
    },
    "Renna Palir": {
      "type": "npc",
      "status": "active",
      "links": [
        "[[Truthkeepers]]",
        "[[Revolar]]",
        "[[Iiko]]",
        "[[Spy of Dusk]]",
        "[[Knights of Dusk]]",
        "[[Chip]]"
      ],
      "tags": [
        "#npc",
        "#lighteyed",
        "#alethi"
      ],
      "last_updated": "2026-05-13T23:29:00"
    },
    "Senny": {
      "type": "npc",
      "status": "active",
      "links": [
        "[[Truthkeepers]]",
        "[[Revolar]]",
        "[[Possessed]]",
        "[[Truthkeeper Camp]]",
        "[[High Witness Yeshan]]",
        "[[Ardent Kaelis]]"
      ],
      "tags": [
        "#npc",
        "#lighteyed",
        "#alethi",
        "#truthkeeper"
      ],
      "last_updated": "2026-05-13T23:35:12"
    },
    "Shallan Davar": {
      "type": "npc",
      "status": "active",
      "links": [
        "[[Ghostbloods]]",
        "[[Kharbranth]]",
        "[[Jasnah Kholin]]",
        "[[Helaran]]",
        "[[Kabsal]]",
        "[[Luesh]]",
        "[[Tyn]]"
      ],
      "tags": [
        "#npc",
        "#lighteyed",
        "#veden",
        "#ghostbloods",
        "#assassin",
        "#apprentice"
      ],
      "last_updated": "2026-05-18T12:00:00"
    },
    "Sila": {
      "type": "npc",
      "status": "active",
      "links": [
        "[[Ghostbloods]]",
        "[[Revolar]]",
        "[[Chip]]",
        "[[Karani]]",
        "[[Adjudicator Peton]]"
      ],
      "tags": [
        "#npc",
        "#darkeyed",
        "#alethi",
        "#ghostbloods",
        "#mercenary"
      ],
      "last_updated": "2026-05-13T23:35:12"
    },
    "Sweeper": {
      "type": "npc",
      "status": "active",
      "links": [
        "[[Ghostbloods]]",
        "[[Revolar]]",
        "[[Chip]]",
        "[[Undertaker]]",
        "[[Nurian Gems]]",
        "[[Bloodmarks]]",
        "[[Truthkeepers]]",
        "[[N'tal]]"
      ],
      "tags": [
        "#npc",
        "#alethi",
        "#contact"
      ],
      "last_updated": "2024-05-25T10:00:00"
    },
    "Szeth-son-son-Vallano": {
      "type": "npc",
      "status": "active",
      "links": [
        "[[Diagram]]",
        "[[Jah Keved]]",
        "[[Galeth-son-Thald]]"
      ],
      "tags": [
        "#npc",
        "#shin",
        "#assassin",
        "#truthless"
      ],
      "last_updated": "2026-05-17T12:00:00"
    },
    "Tahs": {
      "type": "npc",
      "status": "active",
      "links": [
        "[[Truthkeepers]]",
        "[[Revolar]]",
        "[[Karani]]",
        "[[Renna Palir]]"
      ],
      "tags": [
        "#npc",
        "#lighteyed",
        "#alethi",
        "#initiate"
      ],
      "last_updated": "2026-05-13T23:35:12"
    },
    "The Axelsmith": {
      "type": "npc",
      "status": "active",
      "links": [
        "[[Salimset]]",
        "[[Galeth-son-Thald]]",
        "[[011 Promotions and Revolar]]"
      ],
      "tags": [
        "#npc",
        "#darkeyed",
        "#cartwright",
        "#salimset"
      ],
      "last_updated": "2024-05-18T00:00:00"
    },
    "Tien": {
      "type": "npc",
      "status": "active",
      "links": [
        "[[Sadeas Princedom]]",
        "[[Tomat]]",
        "[[Kaladin]]",
        "[[Truthkeepers]]",
        "[[Ghostbloods]]",
        "[[Dillind]]",
        "[[Silent Oath]]",
        "[[Amaram]]"
      ],
      "tags": [
        "#npc",
        "#alethi",
        "#soldier",
        "#sadeas_princedom",
        "#stormblessed"
      ],
      "last_updated": "2024-05-21T09:00:00"
    },
    "Toralin Roshone": {
      "type": "npc",
      "status": "active",
      "links": [
        "[[Sadeas Princedom]]",
        "[[Hearthstone]]",
        "[[Laral Roshone]]",
        "[[Lirin]]",
        "[[Tien]]"
      ],
      "tags": [
        "#npc",
        "#lighteyed",
        "#alethi"
      ],
      "last_updated": "2026-05-13T23:55:00"
    },
    "Undertaker": {
      "type": "npc",
      "status": "active",
      "links": [
        "[[Ghostbloods]]",
        "[[Revolar]]",
        "[[Bruckslats]]",
        "[[N'tal]]",
        "[[Fina]]",
        "[[Truthkeepers]]",
        "[[Silent Oath]]",
        "[[Chip]]",
        "[[Iyatil]]",
        "[[1172-02-18 Meeting with the Undertaker]]"
      ],
      "tags": [
        "#npc",
        "#thaylen",
        "#ghostbloods",
        "#worldhopper"
      ],
      "last_updated": "2026-05-20T15:00:00"
    },
    "Vorn": {
      "type": "npc",
      "status": "active",
      "links": [
        "[[Revolar]]",
        "[[Bodenar]]",
        "[[Ilsh]]",
        "[[Kuma]]"
      ],
      "tags": [
        "#npc",
        "#thaylen",
        "#artifabrian"
      ],
      "last_updated": "2026-05-16T17:00:00"
    },
    "Zabriel": {
      "type": "npc",
      "status": "active",
      "links": [
        "[[Revolar]]",
        "[[Slipmarket]]",
        "[[Bloodmarks]]",
        "[[Nurian Gems]]",
        "[[Undertaker]]"
      ],
      "tags": [
        "#npc",
        "#merchant",
        "#revolar",
        "#captured"
      ],
      "last_updated": "2024-05-25T10:00:00"
    },
    "000 Arrival": {
      "type": "session",
      "status": "completed",
      "links": [
        "[[01 Truthkeepers Arc]]",
        "[[Truthkeeper Camp]]",
        "[[High Witness Yeshan]]",
        "[[Adjudicator Peton]]",
        "[[N'tal]]",
        "[[Kuma]]",
        "[[Iiko]]",
        "[[Fina]]",
        "[[Ojog]]",
        "[[Loid]]",
        "[[High Enforcer Aylen]]",
        "[[Renna Palir]]",
        "[[Koloko]]",
        "[[Sila]]",
        "[[Luggan]]",
        "[[Doug (Guddy)]]"
      ],
      "tags": [
        "#session",
        "#loid",
        "#yolen",
        "#witness",
        "#senny",
        "#quartermaster_jola"
      ],
      "last_updated": "2024-05-24T10:00:00"
    },
    "001 First Blood": {
      "type": "session",
      "status": "completed",
      "links": [
        "[[01 Truthkeepers Arc]]",
        "[[Hearthstone]]",
        "[[Adjudicator Peton]]",
        "[[N'tal]]",
        "[[Ojog]]",
        "[[Truthkeeper Camp]]",
        "[[Luggan]]",
        "[[Doug (Guddy)]]",
        "[[Revolar]]",
        "[[High Witness Yeshan]]",
        "[[Heala]]"
      ],
      "tags": [
        "#session",
        "#Truthkeepers",
        "#Hearthstone",
        "#ShellmiteAttack"
      ],
      "last_updated": "2024-05-24T10:00:00"
    },
    "002 Whitespine": {
      "type": "session",
      "status": "completed",
      "links": [
        "[[01 Truthkeepers Arc]]",
        "[[Hobbleken]]",
        "[[Stringken]]",
        "[[Fina]]",
        "[[Truthkeepers]]",
        "[[Kuma]]",
        "[[N'tal]]",
        "[[Highlord Sadeas]]",
        "[[Ilsh]]",
        "[[Highlord Paladar]]"
      ],
      "tags": [
        "#session",
        "#combat",
        "#investigation"
      ],
      "last_updated": "2026-05-15T18:00:00"
    },
    "003 Yenev and the Axe": {
      "type": "session",
      "status": "completed",
      "links": [
        "[[01 Truthkeepers Arc]]",
        "[[Citylord Nilar Yenev]]",
        "[[Stringken]]",
        "[[Highlady Marise Sathir]]",
        "[[House Sathir]]",
        "[[Dalen]]",
        "[[Ashusa]]",
        "[[Highlord Paladar]]",
        "[[The Axelsmith]]",
        "[[Galeth-son-Thald]]"
      ],
      "tags": [
        "#session",
        "#combat",
        "#investigation"
      ],
      "last_updated": "2024-05-19T16:00:00"
    },
    "004 The Sathir Estate": {
      "type": "session",
      "status": "completed",
      "links": [
        "[[01 Truthkeepers Arc]]",
        "[[House Sathir]]",
        "[[Highlady Marise Sathir]]",
        "[[Mikeyel Franzay]]",
        "[[N'tal]]",
        "[[Kuma]]",
        "[[Mallow]]",
        "[[Iiko]]",
        "[[Dreamwaker]]",
        "[[Glys]]",
        "[[006 Dillind and the Temple]]",
        "[[Galeth-son-Thald]]",
        "[[Fina]]"
      ],
      "tags": [
        "#session",
        "#rp",
        "#downtime"
      ],
      "last_updated": "2024-05-19T16:00:00"
    },
    "005 Hearthstone": {
      "type": "session",
      "status": "completed",
      "links": [
        "[[01 Truthkeepers Arc]]",
        "[[House Sathir|Sathir Estate]]",
        "[[Hearthstone]]",
        "[[Toralin Roshone|Roshones]]",
        "[[House Sathir]]",
        "[[Amaram]]",
        "[[Iiko]]",
        "[[Stringken]]",
        "[[Ilsh]]",
        "[[Lirin]]",
        "[[Hesina]]",
        "[[Galeth-son-Thald]]",
        "[[Fina]]",
        "[[Toralin Roshone]]",
        "[[Laral Roshone]]",
        "[[Renna Palir]]",
        "[[Chip]]",
        "[[Tusa]]",
        "[[Pafo]]"
      ],
      "tags": [
        "#session",
        "#rp",
        "#investigation"
      ],
      "last_updated": "2026-05-15T18:30:00"
    },
    "006 Dillind and the Temple": {
      "type": "session",
      "status": "completed",
      "links": [
        "[[01 Truthkeepers Arc]]",
        "[[Chip]]",
        "[[Morrow]]",
        "[[Dillind]]",
        "[[Lod]]",
        "[[Lavrik]]",
        "[[General Spade]]",
        "[[Iiko]]"
      ],
      "tags": [
        "#session",
        "#combat",
        "#investigation"
      ],
      "last_updated": "2026-05-15T12:00:00"
    },
    "007 Lavrik and the Soulcaster": {
      "type": "session",
      "status": "completed",
      "links": [
        "[[01 Truthkeepers Arc]]",
        "[[Lavrik]]",
        "[[Ardent Vedelis]]",
        "[[Knights of Dusk]]",
        "[[Iiko]]",
        "[[Lod]]",
        "[[Fina]]"
      ],
      "tags": [
        "#session",
        "#combat",
        "#investigation"
      ],
      "last_updated": "2026-05-20T13:00:00"
    },
    "008 The Envisagers of Talinan": {
      "type": "session",
      "status": "completed",
      "links": [
        "[[01 Truthkeepers Arc]]",
        "[[Talinan]]",
        "[[Envisagers]]",
        "[[Dillind]]",
        "[[Iiko]]",
        "[[Tablet of Eleven Cities]]",
        "[[Dreamwaker]]",
        "[[Chip]]",
        "[[Kholinar]]",
        "[[Ghostbloods]]",
        "[[House Sathir]]",
        "[[Highlady Marise Sathir]]"
      ],
      "tags": [
        "#session",
        "#investigation",
        "#combat"
      ],
      "last_updated": "2024-05-19T16:00:00"
    },
    "009 Slavers": {
      "type": "session",
      "status": "completed",
      "links": [
        "[[01 Truthkeepers Arc]]",
        "[[House Sathir]]",
        "[[Revolar]]",
        "[[Hearthstone]]",
        "[[Iiko]]",
        "[[Dreamwaker]]",
        "[[Galeth-son-Thald]]",
        "[[Stringken]]",
        "[[Bloodmarks]]",
        "[[Tusa]]",
        "[[Pafo]]",
        "[[Dillind]]",
        "[[Renna Palir]]"
      ],
      "tags": [
        "#session",
        "#rp",
        "#investigation"
      ],
      "last_updated": "2024-05-19T16:00:00"
    },
    "010 Soulcaster and Shared Employers": {
      "type": "session",
      "status": "completed",
      "links": [
        "[[01 Truthkeepers Arc]]",
        "[[Ashusa]]",
        "[[Truthkeepers]]",
        "[[Galeth-son-Thald]]",
        "[[The Axelsmith]]",
        "[[Kuma]]",
        "[[Soulcaster]]",
        "[[Hobbleken]]",
        "[[Chip]]",
        "[[Possessed]]",
        "[[Truthkeeper Camp]]"
      ],
      "tags": [
        "#session",
        "#combat",
        "#investigation"
      ],
      "last_updated": "2024-05-18T00:00:00"
    },
    "011 Promotions and Revolar": {
      "type": "session",
      "status": "completed",
      "links": [
        "[[01 Truthkeepers Arc]]",
        "[[Adjudicator Peton]]",
        "[[High Enforcer Aylen]]",
        "[[1172-01-35 Morrow's Execution]]",
        "[[Truthkeepers]]",
        "[[Possessed]]",
        "[[Cryptics]]",
        "[[Chip]]",
        "[[Karani]]",
        "[[Ghostbloods]]",
        "[[Bloodmarks]]",
        "[[Revolar]]",
        "[[Knights of Dusk]]",
        "[[Morrow]]",
        "[[N'tal]]",
        "[[Doug (Guddy)]]",
        "[[The Axelsmith]]"
      ],
      "tags": [
        "#session",
        "#promotion",
        "#investigation"
      ],
      "last_updated": "2024-05-18T00:00:00"
    },
    "012 Following Chip": {
      "type": "session",
      "status": "completed",
      "links": [
        "[[02 Knights of Dusk Arc]]",
        "[[Chip]]",
        "[[Karani]]",
        "[[Revolar]]",
        "[[Stackhouses]]",
        "[[Silent Oath]]",
        "[[Truthkeepers]]",
        "[[Cream of the Crem]]",
        "[[Gemheart Inn]]",
        "[[Renna Palir]]",
        "[[Scarstone Quarter]]",
        "[[High Enforcer Aylen]]",
        "[[Knights of Dusk]]",
        "[[Doug (Guddy)]]",
        "[[Iiko]]",
        "[[1172-02-16 The Stackhouse Slavers]]",
        "[[Bloodmarks]]",
        "[[Falen]]",
        "[[Kuma]]"
      ],
      "tags": [
        "#session",
        "#investigation"
      ],
      "last_updated": "2026-05-16T12:00:00"
    },
    "013 Shadow War in the Driftwards": {
      "type": "session",
      "status": "completed",
      "links": [
        "[[02 Knights of Dusk Arc]]",
        "[[Revolar]]",
        "[[Ghostbloods]]",
        "[[Knights of Dusk]]",
        "[[Nurian Gems]]",
        "[[Stackhouses]]",
        "[[Bloodmarks]]",
        "[[Chip]]",
        "[[Karani]]",
        "[[Cream of the Crem]]",
        "[[Whitespine's Fang]]",
        "[[Sweeper]]",
        "[[Undertaker]]",
        "[[N'tal]]",
        "[[Middlecrest]]",
        "[[Sun's Zenith]]",
        "[[Doug (Guddy)]]",
        "[[Zabriel]]",
        "[[Slipmarket]]",
        "[[Mythos]]",
        "[[Shinovar]]",
        "[[Cadence]]",
        "[[Lowstone Alley]]",
        "[[Gemheart Inn]]"
      ],
      "tags": [
        "#session",
        "#investigation",
        "#revolar",
        "#ghostbloods"
      ],
      "last_updated": "2024-05-25T10:00:00"
    },
    "Bloodmarks": {
      "type": "faction",
      "status": "active",
      "links": [
        "[[Bodenar]]",
        "[[Revolar]]",
        "[[Grand Justicar Malice]]",
        "[[Arbiter Jalis]]",
        "[[Vamah Princedom]]",
        "[[N'tal]]",
        "[[Truthkeepers]]",
        "[[Ghostbloods]]"
      ],
      "tags": [
        "#faction",
        "#criminal_organization",
        "#worldhopping"
      ],
      "last_updated": "2024-05-18T00:00:00"
    },
    "Envisagers": {
      "type": "faction",
      "status": "active",
      "links": [
        "[[Truthkeepers]]",
        "[[Possessed]]"
      ],
      "tags": [
        "#faction",
        "#cult"
      ],
      "last_updated": "2026-05-13T23:35:12"
    },
    "Ghostbloods": {
      "type": "faction",
      "status": "active",
      "links": [
        "[[Truthkeepers]]",
        "[[Bloodmarks]]",
        "[[Chip]]",
        "[[Helaran]]",
        "[[Kabsal]]",
        "[[Karani]]",
        "[[Shallan Davar]]",
        "[[Sila]]",
        "[[Sweeper]]",
        "[[Undertaker]]"
      ],
      "tags": [
        "#faction",
        "#secret-society",
        "#espionage"
      ],
      "last_updated": "2026-05-13T23:29:00"
    },
    "Knights of Dusk": {
      "type": "faction",
      "status": "active",
      "links": [
        "[[Revolar]]",
        "[[1172-02-20 The Cinder Evacuation]]",
        "[[Truthkeepers]]",
        "[[Darkstone Forest]]",
        "[[Vamah Princedom]]",
        "[[Bloodmarks]]",
        "[[Ardent Vedelis]]",
        "[[General Spade]]",
        "[[Khria]]",
        "[[Lavrik]]",
        "[[Lila]]"
      ],
      "tags": [
        "#faction"
      ],
      "last_updated": "2026-05-18T12:00:00"
    },
    "Sadeas Princedom": {
      "type": "faction",
      "status": "active",
      "links": [
        "[[Alethkar]]",
        "[[House Sathir]]",
        "[[Highlady Marise Sathir]]",
        "[[Highlord Kethren Sathir]]",
        "[[Amaram]]",
        "[[Tien]]",
        "[[Vamah Princedom]]",
        "[[Truthkeepers]]",
        "[[Possessed]]",
        "[[Knights of Dusk]]",
        "[[Ardent Kaelis]]",
        "[[Ilsh]]",
        "[[Jory]]",
        "[[Lirin]]",
        "[[Morrow]]",
        "[[The Axelsmith]]",
        "[[Vorn]]"
      ],
      "tags": [
        "#faction",
        "#alethi",
        "#military"
      ],
      "last_updated": "2024-05-20T10:00:00"
    },
    "Silent Oath": {
      "type": "faction",
      "status": "active",
      "links": [
        "[[Truthkeepers]]",
        "[[High Enforcer Aylen]]",
        "[[Knights of Dusk]]",
        "[[Istrum]]"
      ],
      "tags": [
        "#faction"
      ],
      "last_updated": "2026-05-13T23:33:15"
    },
    "Sons of Honor": {
      "type": "faction",
      "status": "active",
      "links": [
        "[[Ghostbloods]]"
      ],
      "tags": [
        "#faction",
        "#secret_society",
        "#vorin"
      ],
      "last_updated": "2026-05-16T16:00:00"
    },
    "Truthkeepers": {
      "type": "faction",
      "status": "active",
      "links": [
        "[[Possessed]]",
        "[[High Witness Yeshan]]",
        "[[Revolar]]",
        "[[Knights of Dusk]]",
        "[[Silent Oath]]",
        "[[Vamah Princedom]]",
        "[[Adjudicator Peton]]",
        "[[High Enforcer Aylen]]",
        "[[Renna Palir]]",
        "[[Senny]]",
        "[[Tahs]]"
      ],
      "tags": [
        "#faction"
      ],
      "last_updated": "2026-05-15T12:00:00"
    },
    "Vamah Princedom": {
      "type": "faction",
      "status": "active",
      "links": [
        "[[Revolar]]",
        "[[Highlord Paladar]]",
        "[[General Spade]]",
        "[[General Odrin Lesh]]",
        "[[Sadeas Princedom]]",
        "[[Knights of Dusk]]",
        "[[Truthkeepers]]",
        "[[Citylord Nilar Yenev]]",
        "[[Stringken]]",
        "[[Ashusa]]",
        "[[Possessed]]",
        "[[Bloodmarks]]",
        "[[House Sathir]]",
        "[[Ardent Kaelis]]",
        "[[Ilsh]]",
        "[[Jory]]",
        "[[Lirin]]",
        "[[Morrow]]",
        "[[The Axelsmith]]",
        "[[Vorn]]"
      ],
      "tags": [
        "#faction",
        "#alethi",
        "#revolar",
        "#antagonist"
      ],
      "last_updated": "2024-05-20T10:00:00"
    },
    "Veristitalians": {
      "type": "faction",
      "status": "active",
      "links": [
        "[[Highlord Paladar]]",
        "[[Devotary of Sincerity]]",
        "[[Truthkeepers]]",
        "[[Ardent Vedelis]]",
        "[[Jasnah Kholin]]"
      ],
      "tags": [
        "#faction",
        "#scholar",
        "#devotary"
      ],
      "last_updated": "2026-05-20T13:00:00"
    },
    "Bitter Leaf Apothecary": {
      "type": "location",
      "status": "active",
      "links": [
        "[[Revolar]]"
      ],
      "tags": [
        "#location",
        "#revolar"
      ],
      "last_updated": "2026-05-14T18:30:00"
    },
    "Bodenar": {
      "type": "location",
      "status": "active",
      "links": [
        "[[Jah Keved]]",
        "[[Ghostbloods]]",
        "[[Bloodmarks]]"
      ],
      "tags": [
        "#location",
        "#jah_keved",
        "#trading_hub"
      ],
      "last_updated": "2026-05-17T12:00:00"
    },
    "Boundless Bazaar": {
      "type": "location",
      "status": "active",
      "links": [
        "[[Revolar]]",
        "[[Undertaker]]"
      ],
      "tags": [
        "#location",
        "#revolar"
      ],
      "last_updated": "2026-05-14T20:00:00"
    },
    "Cream of the Crem": {
      "type": "location",
      "status": "active",
      "links": [
        "[[Revolar]]",
        "[[Cuisine of Roshar]]"
      ],
      "tags": [
        "#location",
        "#revolar"
      ],
      "last_updated": "2026-05-19T12:00:00"
    },
    "Darkstone Forest": {
      "type": "location",
      "status": "active",
      "links": [
        "[[Revolar]]",
        "[[Knights of Dusk]]"
      ],
      "tags": [
        "#location",
        "#revolar"
      ],
      "last_updated": "2026-05-15T12:00:00"
    },
    "Hearthstone": {
      "type": "location",
      "status": "active",
      "links": [
        "[[Alethkar]]",
        "[[Truthkeepers]]"
      ],
      "tags": [
        "#location"
      ],
      "last_updated": "2026-05-13T23:35:12"
    },
    "Hobbleken": {
      "type": "location",
      "status": "active",
      "links": [
        "[[Alethkar]]"
      ],
      "tags": [
        "#location"
      ],
      "last_updated": "2026-05-13T23:35:12"
    },
    "House Sathir": {
      "type": "location",
      "status": "active",
      "links": [
        "[[Alethkar]]",
        "[[Sadeas Princedom]]",
        "[[Stringken]]",
        "[[Hobbleken]]",
        "[[Highlord Kethren Sathir]]",
        "[[Highlady Marise Sathir]]",
        "[[Shara Sathir]]",
        "[[Dalen]]",
        "[[Mikeyel Franzay]]",
        "[[Citylord Nilar Yenev]]"
      ],
      "tags": [
        "#location",
        "#alethi",
        "#noble_house"
      ],
      "last_updated": "2024-05-19T16:00:00"
    },
    "Kharbranth": {
      "type": "location",
      "status": "active",
      "links": [],
      "tags": [
        "#location",
        "#city_of_bells"
      ],
      "last_updated": "2026-05-18T12:00:00"
    },
    "Revolar": {
      "type": "location",
      "status": "active",
      "links": [
        "[[Alethkar]]",
        "[[Darkstone Forest]]",
        "[[Scarstone Quarter]]",
        "[[Stackhouses]]",
        "[[Cream of the Crem]]",
        "[[Whitespine's Fang]]",
        "[[Sun's Zenith]]",
        "[[Bitter Leaf Apothecary]]",
        "[[Boundless Bazaar]]",
        "[[The Vamah Archivum]]"
      ],
      "tags": [
        "#location"
      ],
      "last_updated": "2024-05-25T10:00:00"
    },
    "Salimset": {
      "type": "location",
      "status": "active",
      "links": [
        "[[Alethkar]]",
        "[[The Axelsmith]]",
        "[[Chip]]",
        "[[Sweeper]]",
        "[[Morrow]]",
        "[[Truthkeepers]]"
      ],
      "tags": [
        "#location"
      ],
      "last_updated": "2024-05-18T00:00:00"
    },
    "Scarstone Quarter": {
      "type": "location",
      "status": "active",
      "links": [
        "[[Revolar]]",
        "[[1172-02-22 The Foundry Chase]]",
        "[[Bloodmarks]]",
        "[[Possessed]]",
        "[[Stackhouses]]"
      ],
      "tags": [
        "#location",
        "#revolar"
      ],
      "last_updated": "2024-05-18T00:00:00"
    },
    "Stackhouses": {
      "type": "location",
      "status": "active",
      "links": [
        "[[Scarstone Quarter]]",
        "[[Revolar]]",
        "[[Bloodmarks]]",
        "[[Knights of Dusk]]",
        "[[Lila]]",
        "[[1172-02-16 The Stackhouse Slavers]]"
      ],
      "tags": [
        "#location",
        "#revolar"
      ],
      "last_updated": "2026-05-16T12:00:00"
    },
    "Stringken": {
      "type": "location",
      "status": "active",
      "links": [
        "[[Alethkar]]",
        "[[Highlord Sadeas]]",
        "[[Highlord Paladar]]"
      ],
      "tags": [
        "#location"
      ],
      "last_updated": "2026-05-13T23:35:12"
    },
    "Sun's Zenith": {
      "type": "location",
      "status": "active",
      "links": [
        "[[Revolar]]",
        "[[Bloodmarks]]"
      ],
      "tags": [
        "#location",
        "#revolar"
      ],
      "last_updated": "2026-05-15T12:00:00"
    },
    "Talinan": {
      "type": "location",
      "status": "active",
      "links": [
        "[[Alethkar]]",
        "[[Envisagers]]"
      ],
      "tags": [
        "#location"
      ],
      "last_updated": "2026-05-14T14:00:00"
    },
    "The Vamah Archivum": {
      "type": "location",
      "status": "active",
      "links": [
        "[[Revolar]]",
        "[[Truthkeepers]]",
        "[[Renna Palir]]",
        "[[Possessed]]"
      ],
      "tags": [
        "#location",
        "#revolar"
      ],
      "last_updated": "2026-05-15T12:00:00"
    },
    "Tomat": {
      "type": "location",
      "status": "active",
      "links": [
        "[[Alethkar]]",
        "[[Sadeas Princedom]]",
        "[[Amaram]]",
        "[[Tien]]",
        "[[Dillind]]",
        "[[Helaran]]",
        "[[Ghostbloods]]",
        "[[Sons of Honor]]",
        "[[Truthkeepers]]",
        "[[High Enforcer Aylen]]",
        "[[Possessed]]",
        "[[Knights of Dusk]]",
        "[[General Spade]]",
        "[[Silent Oath]]",
        "[[Bloodmarks]]"
      ],
      "tags": [
        "#location",
        "#alethi",
        "#sadeas",
        "#border_town"
      ],
      "last_updated": "2024-05-22T10:00:00"
    },
    "Truthkeeper Camp": {
      "type": "location",
      "status": "active",
      "links": [
        "[[Alethkar]]",
        "[[Truthkeepers]]",
        "[[Possessed]]",
        "[[High Witness Yeshan]]",
        "[[Adjudicator Peton]]"
      ],
      "tags": [
        "#location",
        "#placeholder"
      ],
      "last_updated": "2026-05-13T23:29:00"
    },
    "Whitespine's Fang": {
      "type": "location",
      "status": "active",
      "links": [
        "[[Revolar]]",
        "[[Sweeper]]"
      ],
      "tags": [
        "#location",
        "#revolar"
      ],
      "last_updated": "2026-05-19T12:00:00"
    },
    "Helaran's Shadow": {
      "type": "hook",
      "status": "planned",
      "links": [
        "[[Undertaker]]",
        "[[Tomat]]",
        "[[Helaran]]",
        "[[Chip]]",
        "[[Ghostbloods]]",
        "[[Amaram]]"
      ],
      "tags": [
        "#hook",
        "#ghostbloods",
        "#tomat"
      ],
      "last_updated": "2024-05-22T10:00:00"
    },
    "N'tal's Vendetta": {
      "type": "hook",
      "status": "active",
      "links": [
        "[[Driftwards]]",
        "[[N'tal]]",
        "[[Arbiter Jalis]]",
        "[[Nurian Gems]]",
        "[[Bloodmarks]]",
        "[[Grand Justicar Malice]]"
      ],
      "tags": [
        "#hook",
        "#n_tal",
        "#revenge",
        "#bloodmarks"
      ],
      "last_updated": "2026-05-20T12:00:00"
    },
    "New Technology": {
      "type": "hook",
      "status": "active",
      "links": [
        "[[Vorn]]",
        "[[Kuma]]",
        "[[Stoneweave]]",
        "[[Revolar]]",
        "[[Viscose]]",
        "[[Nurian Gem]]",
        "[[1172-03-42 The Experimental Steamship]]",
        "[[Bodenar]]",
        "[[Nurian Gems]]"
      ],
      "tags": [
        "#hook",
        "#kuma",
        "#nurian_gems",
        "#fabrial"
      ],
      "last_updated": "2026-05-20T12:00:00"
    },
    "Resonance of the Past": {
      "type": "hook",
      "status": "planned",
      "links": [
        "[[Vorn]]",
        "[[Tomat]]",
        "[[Nurian Gems]]",
        "[[Viscose]]",
        "[[Dreamwaker]]",
        "[[Ardent Kaelis]]",
        "[[Iiko]]",
        "[[Kuma]]",
        "[[Tablet of Eleven Cities]]"
      ],
      "tags": [
        "#hook",
        "#tomat",
        "#kuma",
        "#iiko"
      ],
      "last_updated": "2024-05-22T10:00:00"
    },
    "Sila's Allegiance": {
      "type": "hook",
      "status": "active",
      "links": [
        "[[Truthkeeper Camp]]",
        "[[Karani]]",
        "[[Chip]]",
        "[[Ghostbloods]]"
      ],
      "tags": [
        "#hook",
        "#placeholder"
      ],
      "last_updated": "2026-05-13T23:35:12"
    },
    "Spy of Dusk": {
      "type": "hook",
      "status": "active",
      "links": [
        "[[Adjudicator Peton]]",
        "[[Beric Quinn]]",
        "[[Scarstone Quarter]]",
        "[[The Vamah Archivum]]",
        "[[Renna Palir]]",
        "[[Truthkeepers]]",
        "[[Knights of Dusk]]",
        "[[Ojog]]"
      ],
      "tags": [
        "#hook",
        "#revolar"
      ],
      "last_updated": "2024-05-24T12:00:00"
    },
    "The Devotary Call": {
      "type": "hook",
      "status": "active",
      "links": [
        "[[Ardent Kaelis]]",
        "[[Iiko]]",
        "[[Devotary of Sincerity]]",
        "[[The Vamah Archivum]]",
        "[[Veristitalians]]",
        "[[Tablet of Eleven Cities]]"
      ],
      "tags": [
        "#hook",
        "#iiko",
        "#devotary_of_sincerity",
        "#scholar"
      ],
      "last_updated": "2026-05-20T12:00:00"
    },
    "The Highlord's Greed": {
      "type": "hook",
      "status": "active",
      "links": [
        "[[The Vamah Archivum]]",
        "[[Sun's Zenith]]",
        "[[Nomos]]",
        "[[The Bastion]]",
        "[[General Odrin Lesh]]",
        "[[Bloodmarks]]",
        "[[Highlord Paladar]]",
        "[[Revolar]]"
      ],
      "tags": [
        "#hook",
        "#corruption",
        "#highlord_paladar",
        "#bloodmarks"
      ],
      "last_updated": "2026-05-20T12:00:00"
    },
    "The Orphans of Tomat": {
      "type": "hook",
      "status": "planned",
      "links": [
        "[[House Sathir]]",
        "[[Dillind]]",
        "[[Tomat]]",
        "[[Bloodmarks]]",
        "[[Highlady Marise Sathir]]",
        "[[Amaram]]",
        "[[Envisagers]]",
        "[[Mallow]]"
      ],
      "tags": [
        "#hook",
        "#tomat",
        "#mallow",
        "#dillind"
      ],
      "last_updated": "2024-05-22T10:00:00"
    },
    "The Stormblessed Investigation": {
      "type": "hook",
      "status": "planned",
      "links": [
        "[[Adjudicator Peton]]",
        "[[Tomat]]",
        "[[Tien]]",
        "[[Possessed]]",
        "[[Istrum]]",
        "[[Silent Oath]]",
        "[[Truthkeepers]]"
      ],
      "tags": [
        "#hook",
        "#truthkeepers",
        "#tomat"
      ],
      "last_updated": "2024-05-22T10:00:00"
    },
    "The Warehouse Heist": {
      "type": "hook",
      "status": "active",
      "links": [
        "[[General Odrin Lesh]]",
        "[[Knights of Dusk]]",
        "[[Adjudicator Peton]]",
        "[[Renna Palir]]",
        "[[Beric Quinn]]",
        "[[Shield Ring]]",
        "[[Vamah Princedom]]",
        "[[Revolar]]",
        "[[Truthkeepers]]",
        "[[Darkstone Forest]]"
      ],
      "tags": [
        "#hook",
        "#revolar",
        "#knights_of_dusk",
        "#investigation"
      ],
      "last_updated": "2024-05-23T10:00:00"
    },
    "Tracking the Knights of Dusk": {
      "type": "hook",
      "status": "active",
      "links": [
        "[[Stackhouses]]",
        "[[Truthkeepers]]",
        "[[Lila]]",
        "[[Stoneweave]]",
        "[[Khria]]",
        "[[Sadeas Princedom]]",
        "[[Hearthstone]]",
        "[[Kuma]]",
        "[[Ardent Vedelis]]",
        "[[Stormbristle]]",
        "[[Darkstone Forest]]",
        "[[Driftwards]]",
        "[[Scarstone Quarter]]",
        "[[Knights of Dusk]]"
      ],
      "tags": [
        "#hook",
        "#knights_of_dusk",
        "#khria",
        "#investigation"
      ],
      "last_updated": "2026-05-20T12:00:00"
    },
    "-230-01-01 Day of Recreance": {
      "type": "event",
      "status": "completed",
      "links": [],
      "tags": [
        "#event"
      ],
      "last_updated": "2026-05-16T22:27:44"
    },
    "-3300-01-01 Aharietem": {
      "type": "event",
      "status": "completed",
      "links": [],
      "tags": [
        "#event"
      ],
      "last_updated": "2026-05-16T19:22:15"
    },
    "1167-01-01 The Vengeance Pact": {
      "type": "event",
      "status": "completed",
      "links": [
        "[[Szeth-son-son-Vallano]]",
        "[[Shattered Plains]]"
      ],
      "tags": [
        "#event"
      ],
      "last_updated": "2026-05-17T21:03:51"
    },
    "1172-01-11 The Arrival": {
      "type": "event",
      "status": "completed",
      "links": [
        "[[000 Arrival]]",
        "[[Loid]]",
        "[[The Candle and the Mirror]]"
      ],
      "tags": [
        "#event"
      ],
      "last_updated": "2026-05-16T18:18:32"
    },
    "1172-01-12 The Shellmite Attack": {
      "type": "event",
      "status": "completed",
      "links": [
        "[[001 First Blood]]",
        "[[Hearthstone]]"
      ],
      "tags": [
        "#event",
        "#placeholder"
      ],
      "last_updated": "2026-05-13T23:29:00"
    },
    "1172-01-35 Morrow's Execution": {
      "type": "event",
      "status": "completed",
      "links": [
        "[[011 Promotions and Revolar]]",
        "[[High Enforcer Aylen]]",
        "[[Morrow]]"
      ],
      "tags": [
        "#event"
      ],
      "last_updated": "2026-05-16T18:45:50"
    },
    "1172-02-16 The Stackhouse Slavers": {
      "type": "event",
      "status": "completed",
      "links": [
        "[[012 Following Chip]]",
        "[[Chip]]",
        "[[Scarstone Quarter]]",
        "[[Stackhouses]]",
        "[[Bloodmarks]]",
        "[[Kuma]]",
        "[[Falen]]",
        "[[Truthkeepers]]",
        "[[Soulcaster]]",
        "[[N'tal]]",
        "[[Knights of Dusk]]",
        "[[Truthkeepers|Truthkeeper]]",
        "[[Adjudicator Peton]]"
      ],
      "tags": [
        "#event",
        "#combat",
        "#revolar",
        "#bloodmarks"
      ],
      "last_updated": "2026-05-16T12:00:00"
    },
    "1172-02-17 Meeting at the Whitespine": {
      "type": "event",
      "status": "active",
      "links": [
        "[[013 Shadow War in the Driftwards]]",
        "[[Whitespine's Fang]]",
        "[[N'tal]]",
        "[[Undertaker]]",
        "[[Chip]]",
        "[[Sweeper]]",
        "[[Ghostbloods]]",
        "[[Scarstone Quarter]]",
        "[[1172-02-16 The Stackhouse Slavers]]",
        "[[Bruckslats]]",
        "[[Bloodmarks]]",
        "[[Nurian Gems]]",
        "[[Driftwards]]",
        "[[Truthkeepers]]",
        "[[Senny]]"
      ],
      "tags": [
        "#event",
        "#revolar",
        "#ghostbloods",
        "#investigation"
      ],
      "last_updated": "2026-05-20T14:00:00"
    },
    "1172-02-18 Meeting with the Undertaker": {
      "type": "event",
      "status": "active",
      "links": [
        "[[013 Shadow War in the Driftwards]]",
        "[[Whitespine's Fang]]",
        "[[Bruckslats]]",
        "[[Scarstone Quarter]]",
        "[[Undertaker]]",
        "[[N'tal]]",
        "[[Fina]]",
        "[[Bloodmarks]]",
        "[[Arbiter Jalis]]",
        "[[Stackhouses]]",
        "[[1172-02-17 The Foundry Chase]]"
      ],
      "tags": [
        "#event",
        "#ghostbloods",
        "#revolar",
        "#revelation"
      ],
      "last_updated": "2026-05-20T15:00:00"
    },
    "1172-02-20 The Cinder Evacuation": {
      "type": "event",
      "status": "active",
      "links": [
        "[[Skyglass District]]",
        "[[Revolar]]",
        "[[Highlord Paladar]]",
        "[[Knights of Dusk]]",
        "[[Chip]]"
      ],
      "tags": [
        "#event",
        "#revolar",
        "#investigation",
        "#combat",
        "#fire"
      ],
      "last_updated": "2026-05-18T12:00:00"
    },
    "1172-02-22 The Foundry Chase": {
      "type": "event",
      "status": "active",
      "links": [
        "[[013 Shadow War in the Driftwards]]",
        "[[Scarstone Quarter]]",
        "[[Bruckslats]]",
        "[[Bloodmarks]]",
        "[[Arbiter Jalis]]",
        "[[N'tal]]",
        "[[Jory]]"
      ],
      "tags": [
        "#event",
        "#revolar",
        "#combat",
        "#moral_trial",
        "#chase"
      ],
      "last_updated": "2026-05-20T15:00:00"
    },
    "1172-02-32 The Darkstone Siege": {
      "type": "event",
      "status": "active",
      "links": [
        "[[02 Knights of Dusk Arc]]",
        "[[Darkstone Forest]]",
        "[[Knights of Dusk]]",
        "[[Truthkeepers]]",
        "[[Silent Oath]]",
        "[[General Spade]]",
        "[[Khria]]",
        "[[Adjudicator Peton]]",
        "[[Istrum]]",
        "[[Revolar]]"
      ],
      "tags": [
        "#event",
        "#revolar",
        "#combat",
        "#darkstone_forest"
      ],
      "last_updated": "2026-05-18T12:00:00"
    },
    "1172-03-42 The Experimental Steamship": {
      "type": "event",
      "status": "planned",
      "links": [
        "[[Bodenar]]",
        "[[Nurian Gems]]",
        "[[Bloodmarks]]",
        "[[Vorn]]",
        "[[Ilsh]]",
        "[[Kuma]]"
      ],
      "tags": [
        "#event",
        "#bodenar",
        "#fabrial"
      ],
      "last_updated": "2026-05-17T12:00:00"
    },
    "Cremwidow Poison": {
      "type": "item",
      "status": "active",
      "links": [
        "[[Fina]]"
      ],
      "tags": [
        "#item"
      ],
      "last_updated": "2026-05-17T00:00:00"
    },
    "Cuisine of Roshar": {
      "type": "lore",
      "status": "active",
      "links": [
        "[[Flangria]]"
      ],
      "tags": [
        "#lore",
        "#culture",
        "#cuisine"
      ],
      "last_updated": "2026-05-19T12:00:00"
    },
    "Flora and Fauna": {
      "type": "lore",
      "status": "active",
      "links": [
        "[[KwW8NFI0l-VOu3VGfxH3E|Whitespines]]"
      ],
      "tags": [
        "#location"
      ],
      "last_updated": "2026-05-16T22:25:46"
    },
    "Minor NPCs": {
      "type": "lore",
      "status": "active",
      "links": [
        "[[000 Arrival]]",
        "[[Truthkeeper Camp]]",
        "[[001 First Blood]]",
        "[[Salimset]]",
        "[[002 Whitespine]]",
        "[[Hobbleken]]",
        "[[005 Hearthstone]]",
        "[[Hearthstone]]",
        "[[004 The Sathir Estate]]",
        "[[003 Yenev and the Axe]]",
        "[[Stringken]]",
        "[[House Sathir]]",
        "[[009 Slavers]]",
        "[[006 Dillind and the Temple]]",
        "[[Hook: The Fieldwards Heist]]",
        "[[Revolar]]",
        "[[013 Shadow War in the Driftwards]]",
        "[[Stackhouses]]",
        "[[012 Following Chip]]"
      ],
      "tags": [
        "#lore",
        "#npc",
        "#reference"
      ],
      "last_updated": "2024-05-25T10:00:00"
    },
    "Nurian Gems": {
      "type": "lore",
      "status": "active",
      "links": [
        "[[1172-03-42 The Experimental Steamship]]",
        "[[Bloodmarks]]",
        "[[Grand Justicar Malice]]"
      ],
      "tags": [
        "#lore",
        "#gemstone",
        "#fabrial"
      ],
      "last_updated": "2026-05-17T12:00:00"
    },
    "Orders of the Knights Radiant": {
      "type": "lore",
      "status": "active",
      "links": [
        "[[High Enforcer Aylen]]",
        "[[High Witness Yeshan]]",
        "[[Silent Oath]]",
        "[[Truthkeepers]]",
        "[[Pyre]]",
        "[[N'tal]]",
        "[[General Spade]]",
        "[[Verdae]]",
        "[[Fina]]",
        "[[Dreamwaker]]",
        "[[Iiko]]",
        "[[Khria]]",
        "[[Possessed]]",
        "[[Morrow]]",
        "[[Viscose]]",
        "[[Kuma]]",
        "[[Jasnah Kholin]]",
        "[[Cadence]]",
        "[[Mallow]]",
        "[[Kun'ahu]]",
        "[[Galeth-son-Thald]]"
      ],
      "tags": [
        "#lore",
        "#knights_radiant",
        "#surgebinding",
        "#oaths"
      ],
      "last_updated": "2024-05-19T12:00:00"
    },
    "Possessed": {
      "type": "lore",
      "status": "active",
      "links": [
        "[[Truthkeepers]]",
        "[[Orders of the Knights Radiant]]",
        "[[High Enforcer Aylen]]",
        "[[High Witness Yeshan]]"
      ],
      "tags": [
        "#lore",
        "#placeholder"
      ],
      "last_updated": "2024-05-19T12:00:00"
    },
    "Prophecy of Ten Keys": {
      "type": "lore",
      "status": "active",
      "links": [],
      "tags": [
        "#lore",
        "#prophecy",
        "#urithiru"
      ],
      "last_updated": "2024-05-19T15:00:00"
    },
    "Tablet of Eleven Cities": {
      "type": "lore",
      "status": "active",
      "links": [
        "[[Urithiru]]",
        "[[Dreamwaker]]",
        "[[Truthkeepers]]",
        "[[Kholinar]]",
        "[[Rall Elorim]]",
        "[[Narak]]",
        "[[Shattered Plains]]",
        "[[Azimir]]",
        "[[High Witness Yeshan]]",
        "[[Thaylen City]]",
        "[[Kharbranth]]",
        "[[Vedenar]]"
      ],
      "tags": [
        "#lore",
        "#prophecy",
        "#dawncities",
        "#silver_kingdoms",
        "#urithiru"
      ],
      "last_updated": "2024-05-19T15:00:00"
    },
    "The Candle and the Mirror": {
      "type": "lore",
      "status": "active",
      "links": [],
      "tags": [
        "#location"
      ],
      "last_updated": "2026-05-16T18:21:53"
    },
    "The Steamship's Secret": {
      "type": "lore",
      "status": "active",
      "links": [
        "[[1172-03-42 The Experimental Steamship]]",
        "[[Nurian Gems]]",
        "[[Grand Justicar Malice]]",
        "[[Bloodmarks]]",
        "[[Kuma]]",
        "[[Vorn]]"
      ],
      "tags": [
        "#lore",
        "#secret",
        "#bodenar"
      ],
      "last_updated": "2026-05-17T12:00:00"
    },
    "Cadence": {
      "type": "spren",
      "status": "active",
      "links": [
        "[[Mallow]]",
        "[[Truthkeepers]]"
      ],
      "tags": [
        "#spren",
        "#lightspren",
        "#reacher"
      ],
      "last_updated": "2026-05-13T23:35:12"
    },
    "Dreamwaker": {
      "type": "spren",
      "status": "active",
      "links": [
        "[[Iiko]]",
        "[[Tablet of Eleven Cities]]"
      ],
      "tags": [
        "#spren",
        "#mistspren",
        "#ancient"
      ],
      "last_updated": "2024-05-19T15:00:00"
    },
    "Kun'ahu": {
      "type": "spren",
      "status": "active",
      "links": [
        "[[Galeth-son-Thald]]"
      ],
      "tags": [
        "#spren",
        "#peakspren",
        "#reliable"
      ],
      "last_updated": "2026-05-13T23:29:00"
    },
    "Pyre": {
      "type": "spren",
      "status": "active",
      "links": [
        "[[N'tal]]",
        "[[Ghostbloods]]"
      ],
      "tags": [
        "#spren",
        "#ashspren",
        "#radiant"
      ],
      "last_updated": "2026-05-13T23:29:00"
    },
    "Verdae": {
      "type": "spren",
      "status": "active",
      "links": [
        "[[Fina]]"
      ],
      "tags": [
        "#spren",
        "#cultivationspren",
        "#naive"
      ],
      "last_updated": "2026-05-13T23:29:00"
    },
    "Viscose": {
      "type": "spren",
      "status": "active",
      "links": [
        "[[Kuma]]"
      ],
      "tags": [
        "#spren",
        "#inkspren",
        "#logical"
      ],
      "last_updated": "2026-05-13T23:29:00"
    }
  }
}